datasette_basemap/__init__.py
datasette_basemap/data/basemap.db
datasette_basemap-0.2.dist-info/METADATA
datasette_basemap-0.2.dist-info/WHEEL
datasette_basemap-0.2.dist-info/entry_points.txt
datasette_basemap-0.2.dist-info/top_level.txt
datasette_basemap-0.2.dist-info/RECORD
