Metadata-Version: 2.1
Name: datasette-basemap
Version: 0.2
Summary: A basemap for Datasette and datasette-leaflet
Home-page: https://github.com/simonw/datasette-basemap
Author: Simon Willison
License: Apache License, Version 2.0
Project-URL: Issues, https://github.com/simonw/datasette-basemap/issues
Project-URL: CI, https://github.com/simonw/datasette-basemap/actions
Project-URL: Changelog, https://github.com/simonw/datasette-basemap/releases
Platform: UNKNOWN
Requires-Python: >=3.6
Requires-Dist: datasette
Provides-Extra: test
Requires-Dist: pytest ; extra == 'test'
Requires-Dist: pytest-asyncio ; extra == 'test'
